summrai/__init__.py
summrai/client.py
summrai/utils.py
summrai-0.1.1.dist-info/METADATA
summrai-0.1.1.dist-info/WHEEL
summrai-0.1.1.dist-info/top_level.txt
summrai-0.1.1.dist-info/RECORD
