Metadata-Version: 2.4
Name: summrai
Version: 0.1.1
Summary: Secure AI helper library using external API keys and free Gemini models.
Author: Your Name
Author-email: Jiyo P V <jiyopv21@gmail.com>
License: MIT
Project-URL: Homepage, https://pypi.org/project/summrai/
Project-URL: Source, https://github.com/jiyo-pv/summrai
Keywords: AI,NLP,Gemini,text-generation,summarization
Requires-Python: >=3.8
Requires-Dist: requests
